{"cameraMode":{"drawMode":0,"name":"Shaded","section":"Shading Mode"},"sceneLighting":true,"audioPlay":false,"sceneViewState":{"showFog":true,"showMaterialUpdate":false,"showSkybox":true,"showFlares":true,"showImageEffects":true,"showParticleSystems":true},"in2DMode":false,"pivot":{"x":-7.443592548370361,"y":8.938301086425782,"z":7.3408355712890629},"rotation":{"x":0.37738946080207827,"y":0.5987290143966675,"z":-0.37898099422454836,"w":0.5962258577346802},"size":70.71440124511719,"orthographic":false}